{"assets":{"67FF8A6F696DDF5D140FEE233C4D1A3E":{"type":"texture","index":2,"assetRequest":{"type":"slide","state":"contents","slide":"none"},"url":{"native":"assets\/5B1D957E-0F9B-41B1-A86B-D7615EC03BE4.pdf"},"width":910,"height":514},"A32DD74C89F5B70158BC841E1CA6D0DB":{"type":"texture","index":1,"assetRequest":{"type":"slide","state":"contents","slide":"none"},"url":{"native":"assets\/5B1D957E-0F9B-41B1-A86B-D7615EC03BE4.pdf"},"width":601,"height":40},"894F4F28C10671A3EF251E2272519862":{"type":"texture","index":5,"assetRequest":{"type":"slide","state":"contents","slide":"none"},"url":{"native":"assets\/5B1D957E-0F9B-41B1-A86B-D7615EC03BE4.pdf"},"width":1024,"height":768},"95EFA5516623AF8CD888B81A922734DB":{"type":"texture","index":0,"assetRequest":{"type":"slide","state":"contents","slide":"none"},"url":{"native":"assets\/5B1D957E-0F9B-41B1-A86B-D7615EC03BE4.pdf"},"width":1024,"height":768},"348B4358EA6B1B32B6E8355B3E2B94E1":{"type":"texture","index":3,"assetRequest":{"type":"slide","state":"contents","slide":"none"},"url":{"native":"assets\/5B1D957E-0F9B-41B1-A86B-D7615EC03BE4.pdf"},"width":731,"height":412},"A368F5FCC70D94AF31308A4D34DC4497":{"type":"texture","index":4,"assetRequest":{"type":"slide","state":"contents","slide":"none"},"url":{"native":"assets\/5B1D957E-0F9B-41B1-A86B-D7615EC03BE4.pdf"},"width":1024,"height":768}},"events":[{"effects":[{"beginTime":0,"baseLayer":{"animations":[],"initialState":{"affineTransform":[1,0,0,1,0,0],"masksToBounds":false,"rotation":0,"scale":1,"position":{"pointX":513.40130615234375,"pointY":435.68824577331543},"width":731,"sublayerTransform":[1,0,0,0,0,1,0,0,0,0,1,0,0,0,0,1],"contentsRect":{"y":0,"x":0,"width":1,"height":1},"opacity":1,"edgeAntialiasingMask":251658240,"height":412,"hidden":false,"anchorPoint":{"pointX":0.5,"pointY":0.5}},"objectID":"9B3EB161-0271-4642-8AF8-C108C7C01EAD","layers":[{"animations":[],"initialState":{"affineTransform":[1,0,0,1,0,0],"masksToBounds":false,"rotation":0,"scale":1,"position":{"pointX":364.09869384765625,"pointY":154.31175422668457},"width":731,"sublayerTransform":[1,0,0,0,0,1,0,0,0,0,1,-0.00049229876906403734,0,0,0,1],"contentsRect":{"y":0,"x":0,"width":1,"height":1},"opacity":1,"edgeAntialiasingMask":251658240,"height":412,"hidden":false,"anchorPoint":{"pointX":0.49808302851936559,"pointY":0.37454309278321496}},"layers":[{"animations":[{"additive":false,"timeOffset":0,"beginTime":1e-100,"repeatCount":0,"fillMode":"both","duration":0.01,"autoreverses":false,"animations":[{"additive":false,"timeOffset":0,"beginTime":0,"from":{"scalar":true},"repeatCount":0,"fillMode":"removed","duration":0.01,"autoreverses":false,"property":"isPlaying","to":{"scalar":true},"removedOnCompletion":true},{"additive":false,"timeOffset":0,"beginTime":0,"from":{"scalar":false},"repeatCount":0,"fillMode":"removed","duration":0.01,"autoreverses":false,"property":"hidden","to":{"scalar":false},"removedOnCompletion":true}],"removedOnCompletion":false}],"layers":[],"texturedRectangle":{"isBackgroundTexture":true,"singleTextureOpacity":1,"textureType":5,"textBaseline":0,"textXHeight":0,"isVerticalText":false},"initialState":{"affineTransform":[1,0,0,1,0,0],"masksToBounds":false,"rotation":0,"scale":1,"position":{"pointX":364.59869384765625,"pointY":205.3117542266846},"width":731,"sublayerTransform":[1,0,0,0,0,1,0,0,0,0,1,0,0,0,0,1],"contentsRect":{"y":0,"x":0,"width":1,"height":1},"opacity":1,"edgeAntialiasingMask":0,"height":412,"hidden":false,"anchorPoint":{"pointX":0.5,"pointY":0.5}},"texture":"348B4358EA6B1B32B6E8355B3E2B94E1"}]}]},"effects":[{"objectID":"9B3EB161-0271-4642-8AF8-C108C7C01EAD","beginTime":0,"baseLayer":{"animations":[],"initialState":{"affineTransform":[1,0,0,1,0,0],"masksToBounds":false,"rotation":0,"scale":1,"position":{"pointX":513.40130615234375,"pointY":435.68824577331543},"width":731,"sublayerTransform":[1,0,0,0,0,1,0,0,0,0,1,0,0,0,0,1],"contentsRect":{"y":0,"x":0,"width":1,"height":1},"opacity":1,"edgeAntialiasingMask":251658240,"height":412,"hidden":false,"anchorPoint":{"pointX":0.5,"pointY":0.5}},"objectID":"9B3EB161-0271-4642-8AF8-C108C7C01EAD","layers":[{"animations":[],"initialState":{"affineTransform":[1,0,0,1,0,0],"masksToBounds":false,"rotation":0,"scale":1,"position":{"pointX":364.09869384765625,"pointY":154.31175422668457},"width":731,"sublayerTransform":[1,0,0,0,0,1,0,0,0,0,1,-0.00049229876906403734,0,0,0,1],"contentsRect":{"y":0,"x":0,"width":1,"height":1},"opacity":1,"edgeAntialiasingMask":251658240,"height":412,"hidden":false,"anchorPoint":{"pointX":0.49808302851936559,"pointY":0.37454309278321496}},"layers":[{"animations":[{"additive":false,"timeOffset":0,"beginTime":1e-100,"repeatCount":0,"fillMode":"both","duration":0.01,"autoreverses":false,"animations":[{"additive":false,"timeOffset":0,"beginTime":0,"from":{"scalar":true},"repeatCount":0,"fillMode":"removed","duration":0.01,"autoreverses":false,"property":"isPlaying","to":{"scalar":true},"removedOnCompletion":true},{"additive":false,"timeOffset":0,"beginTime":0,"from":{"scalar":false},"repeatCount":0,"fillMode":"removed","duration":0.01,"autoreverses":false,"property":"hidden","to":{"scalar":false},"removedOnCompletion":true}],"removedOnCompletion":false}],"layers":[],"isWebVideoPosterLayer":true,"initialState":{"affineTransform":[1,0,0,1,0,0],"masksToBounds":false,"rotation":0,"scale":1,"position":{"pointX":364.59869384765625,"pointY":205.3117542266846},"width":731,"sublayerTransform":[1,0,0,0,0,1,0,0,0,0,1,0,0,0,0,1],"contentsRect":{"y":0,"x":0,"width":1,"height":1},"opacity":1,"edgeAntialiasingMask":0,"height":412,"hidden":false,"anchorPoint":{"pointX":0.5,"pointY":0.5}},"texturedRectangle":{"isBackgroundTexture":true,"singleTextureOpacity":1,"textureType":5,"textBaseline":0,"textXHeight":0,"isVerticalText":false},"texture":"348B4358EA6B1B32B6E8355B3E2B94E1"}]}]},"effects":[],"duration":0,"type":"buildIn","webVideo":{"url":"https:\/\/www.youtube.com\/watch?v=0ZQJnOgYB4U"},"name":"renderWebVideo","attributes":{"direction":0}}],"duration":0.01,"type":"buildIn","attributes":{"direction":0},"name":"apple:web-video-start","objectID":"9B3EB161-0271-4642-8AF8-C108C7C01EAD"}],"automaticPlay":false,"hyperlinks":[],"accessibility":[{"text":"2.4 Modificación Resultados de Aprendizaje","targetRectangle":{"y":79.818023681640625,"x":212.69708984375001,"width":598.60582031249987,"height":45}}],"baseLayer":{"animations":[],"initialState":{"affineTransform":[1,0,0,1,0,0],"masksToBounds":false,"rotation":0,"scale":1,"position":{"pointX":512,"pointY":384},"width":1024,"sublayerTransform":[1,0,0,0,0,1,0,0,0,0,1,0,0,0,0,1],"contentsRect":{"y":0,"x":0,"width":1,"height":1},"opacity":1,"edgeAntialiasingMask":251658240,"height":768,"hidden":false,"anchorPoint":{"pointX":0.5,"pointY":0.5}},"layers":[{"animations":[],"initialState":{"affineTransform":[1,0,0,1,0,0],"masksToBounds":false,"rotation":0,"scale":1,"position":{"pointX":512,"pointY":384},"width":1024,"sublayerTransform":[1,0,0,0,0,1,0,0,0,0,1,0,0,0,0,1],"contentsRect":{"y":0,"x":0,"width":1,"height":1},"opacity":1,"edgeAntialiasingMask":251658240,"height":768,"hidden":false,"anchorPoint":{"pointX":0.5,"pointY":0.5}},"layers":[{"animations":[],"initialState":{"affineTransform":[1,0,0,1,0,0],"masksToBounds":false,"rotation":0,"scale":1,"position":{"pointX":512,"pointY":384},"width":1024,"sublayerTransform":[1,0,0,0,0,1,0,0,0,0,1,0,0,0,0,1],"contentsRect":{"y":0,"x":0,"width":1,"height":1},"opacity":1,"edgeAntialiasingMask":251658240,"height":768,"hidden":false,"anchorPoint":{"pointX":0.5,"pointY":0.5}},"layers":[{"animations":[],"layers":[],"texturedRectangle":{"isBackgroundTexture":true,"singleTextureOpacity":1,"textureType":1,"textBaseline":0,"textXHeight":0,"isVerticalText":false},"initialState":{"affineTransform":[1,0,0,1,0,0],"masksToBounds":false,"rotation":0,"scale":1,"position":{"pointX":512,"pointY":384},"width":1024,"sublayerTransform":[1,0,0,0,0,1,0,0,0,0,1,0,0,0,0,1],"contentsRect":{"y":0,"x":0,"width":1,"height":1},"opacity":1,"edgeAntialiasingMask":0,"height":768,"hidden":false,"anchorPoint":{"pointX":0.5,"pointY":0.5}},"texture":"95EFA5516623AF8CD888B81A922734DB"}]}]},{"animations":[],"initialState":{"affineTransform":[1,0,0,1,0,0],"masksToBounds":false,"rotation":0,"scale":1,"position":{"pointX":512,"pointY":384},"width":1024,"sublayerTransform":[1,0,0,0,0,1,0,0,0,0,1,0,0,0,0,1],"contentsRect":{"y":0,"x":0,"width":1,"height":1},"opacity":1,"edgeAntialiasingMask":251658240,"height":768,"hidden":false,"anchorPoint":{"pointX":0.5,"pointY":0.5}},"layers":[{"animations":[],"initialState":{"affineTransform":[1,0,0,1,0,0],"masksToBounds":false,"rotation":0,"scale":1,"position":{"pointX":509.11297607421875,"pointY":95.818023681640625},"width":601,"sublayerTransform":[1,0,0,0,0,1,0,0,0,0,1,0,0,0,0,1],"contentsRect":{"y":0,"x":0,"width":1,"height":1},"opacity":1,"edgeAntialiasingMask":251658240,"height":40,"hidden":false,"anchorPoint":{"pointX":0.5,"pointY":0.5}},"layers":[{"animations":[],"layers":[],"texturedRectangle":{"singleTextureOpacity":1,"textXHeight":0.41036901855468749,"textBaseline":0.72626406860351567,"isBackgroundTexture":true,"isVerticalText":false,"textColor":[0.42432993650436401,0.41137170791625977,0.38714420795440674,1],"textureType":6},"initialState":{"affineTransform":[1,0,0,1,0,0],"masksToBounds":false,"rotation":0,"scale":1,"position":{"pointX":303.88702392578125,"pointY":30.181976318359375},"width":601,"sublayerTransform":[1,0,0,0,0,1,0,0,0,0,1,0,0,0,0,1],"contentsRect":{"y":0,"x":0,"width":1,"height":1},"opacity":1,"edgeAntialiasingMask":0,"height":40,"hidden":false,"anchorPoint":{"pointX":0.5,"pointY":0.5}},"texture":"A32DD74C89F5B70158BC841E1CA6D0DB"}]}]},{"animations":[],"initialState":{"affineTransform":[1,0,0,1,0,0],"masksToBounds":false,"rotation":0,"scale":1,"position":{"pointX":512,"pointY":384},"width":1024,"sublayerTransform":[1,0,0,0,0,1,0,0,0,0,1,0,0,0,0,1],"contentsRect":{"y":0,"x":0,"width":1,"height":1},"opacity":1,"edgeAntialiasingMask":251658240,"height":768,"hidden":false,"anchorPoint":{"pointX":0.5,"pointY":0.5}},"layers":[{"animations":[],"initialState":{"affineTransform":[1,0,0,1,0,0],"masksToBounds":false,"rotation":0,"scale":1,"position":{"pointX":518.02183532714844,"pointY":445.6427001953125},"width":910,"sublayerTransform":[1,0,0,0,0,1,0,0,0,0,1,0,0,0,0,1],"contentsRect":{"y":0,"x":0,"width":1,"height":1},"opacity":1,"edgeAntialiasingMask":251658240,"height":514,"hidden":false,"anchorPoint":{"pointX":0.5,"pointY":0.5}},"layers":[{"animations":[],"layers":[],"texturedRectangle":{"singleTextureOpacity":1,"textXHeight":0,"shapePath":{"lineWidth":1,"flatness":0.59999999999999998,"lineCapStyle":0,"elements":[{"type":"MoveToPoint","points":[[87.164935424923897,5.6427001953125]]},{"type":"AddCurve","points":[[65.107605470922863,5.6427001953125],[65.852472043951821,23.59053465239117],[65.852480687201023,45.647806264460087]]},{"type":"AddLine","points":[[65.852480687201023,455.75324759632349]]},{"type":"AddLine","points":[[6.0218353271484375,455.75324759632349]]},{"type":"AddCurve","points":[[6.0218353271484375,455.75324759632349],[6.0218353271484375,468.83985292195939],[6.0218353271484375,483.72141909599304]]},{"type":"AddCurve","points":[[6.0218353271484375,508.66988133525956],[13.914665749490837,508.64495420455933],[43.265526995062828,508.64495420455933]]},{"type":"AddLine","points":[[435.52798296511173,508.64495420455933]]},{"type":"AddLine","points":[[474.47100657224655,508.64495420455933]]},{"type":"AddLine","points":[[866.73346254229546,508.64495420455933]]},{"type":"AddCurve","points":[[894.28530601437524,508.64495420455933],[903.97715421020985,508.67423753285766],[903.97715421020985,483.72141909599304]]},{"type":"AddCurve","points":[[903.97943602799933,468.84206559375525],[903.97715421020985,455.75338588831073],[903.97715421020985,455.75324759632349]]},{"type":"AddLine","points":[[844.14650885015726,455.75324759632349]]},{"type":"AddLine","points":[[844.14650885015726,45.647806264460087]]},{"type":"AddCurve","points":[[844.14650885015726,23.590477390865203],[845.60168628590327,5.6427409792804895],[823.54210908710957,5.6427001953125]]},{"type":"AddLine","points":[[87.164935424923897,5.6427001953125]]},{"type":"CloseSubpath"},{"type":"MoveToPoint","points":[[108.90222314745188,48.692442655563354]]},{"type":"AddLine","points":[[801.09676638990641,48.692442655563354]]},{"type":"AddLine","points":[[801.09676638990641,455.75324759632349]]},{"type":"AddLine","points":[[474.47100657224655,455.75324759632349]]},{"type":"AddLine","points":[[435.52798296511173,455.75324759632349]]},{"type":"AddLine","points":[[108.90222314745188,455.75324759632349]]},{"type":"AddLine","points":[[108.90222314745188,48.692442655563354]]},{"type":"CloseSubpath"},{"type":"MoveToPoint","points":[[108.90222314745188,48.692442655563354]]}],"windingRule":0,"lineJoinStyle":0,"miterLimit":10},"isBackgroundTexture":true,"textBaseline":0,"isVerticalText":false,"textureType":5},"initialState":{"affineTransform":[1,0,0,1,0,0],"masksToBounds":false,"rotation":0,"scale":1,"position":{"pointX":448.97816467285156,"pointY":251.3572998046875},"width":910,"sublayerTransform":[1,0,0,0,0,1,0,0,0,0,1,0,0,0,0,1],"contentsRect":{"y":0,"x":0,"width":1,"height":1},"opacity":1,"edgeAntialiasingMask":0,"height":514,"hidden":false,"anchorPoint":{"pointX":0.5,"pointY":0.5}},"texture":"67FF8A6F696DDF5D140FEE233C4D1A3E"}]}]},{"animations":[],"initialState":{"affineTransform":[1,0,0,1,0,0],"masksToBounds":false,"rotation":0,"scale":1,"position":{"pointX":512,"pointY":384},"width":1024,"sublayerTransform":[1,0,0,0,0,1,0,0,0,0,1,0,0,0,0,1],"contentsRect":{"y":0,"x":0,"width":1,"height":1},"opacity":1,"edgeAntialiasingMask":251658240,"height":768,"hidden":false,"anchorPoint":{"pointX":0.5,"pointY":0.5}},"layers":[{"animations":[],"initialState":{"affineTransform":[1,0,0,1,0,0],"masksToBounds":false,"rotation":0,"scale":1,"position":{"pointX":513.40130615234375,"pointY":435.68824577331543},"width":731,"sublayerTransform":[1,0,0,0,0,1,0,0,0,0,1,0,0,0,0,1],"contentsRect":{"y":0,"x":0,"width":1,"height":1},"opacity":1,"edgeAntialiasingMask":251658240,"height":412,"hidden":false,"anchorPoint":{"pointX":0.5,"pointY":0.5}},"objectID":"9B3EB161-0271-4642-8AF8-C108C7C01EAD","layers":[{"animations":[],"layers":[],"texturedRectangle":{"isBackgroundTexture":true,"singleTextureOpacity":1,"textureType":5,"textBaseline":0,"textXHeight":0,"isVerticalText":false},"initialState":{"affineTransform":[1,0,0,1,0,0],"masksToBounds":false,"rotation":0,"scale":1,"position":{"pointX":364.59869384765625,"pointY":205.3117542266846},"width":731,"sublayerTransform":[1,0,0,0,0,1,0,0,0,0,1,0,0,0,0,1],"contentsRect":{"y":0,"x":0,"width":1,"height":1},"opacity":1,"edgeAntialiasingMask":0,"height":412,"hidden":false,"anchorPoint":{"pointX":0.5,"pointY":0.5}},"texture":"348B4358EA6B1B32B6E8355B3E2B94E1"}]}]}]}},{"effects":[{"beginTime":0,"baseLayer":{"animations":[],"initialState":{"affineTransform":[1,0,0,1,0,0],"masksToBounds":false,"rotation":0,"scale":1,"position":{"pointX":512,"pointY":384},"width":1024,"sublayerTransform":[1,0,0,0,0,1,0,0,0,0,1,0,0,0,0,1],"contentsRect":{"y":0,"x":0,"width":1,"height":1},"opacity":1,"edgeAntialiasingMask":251658240,"height":768,"hidden":false,"anchorPoint":{"pointX":0.5,"pointY":0.5}},"objectID":"0","layers":[{"animations":[],"initialState":{"affineTransform":[1,0,0,1,0,0],"masksToBounds":false,"rotation":0,"scale":1,"position":{"pointX":512,"pointY":384},"width":1024,"sublayerTransform":[1,0,0,0,0,1,0,0,0,0,1,-0.00049229876906403734,0,0,0,1],"contentsRect":{"y":0,"x":0,"width":1,"height":1},"opacity":1,"edgeAntialiasingMask":251658240,"height":768,"hidden":false,"anchorPoint":{"pointX":0.5,"pointY":0.5}},"layers":[{"animations":[],"layers":[],"texturedRectangle":{"isBackgroundTexture":false,"singleTextureOpacity":1,"textureType":0,"textBaseline":0,"textXHeight":0,"isVerticalText":false},"initialState":{"affineTransform":[1,0,0,1,0,0],"masksToBounds":false,"rotation":0,"scale":1,"position":{"pointX":512,"pointY":384},"width":1024,"sublayerTransform":[1,0,0,0,0,1,0,0,0,0,1,0,0,0,0,1],"contentsRect":{"y":0,"x":0,"width":1,"height":1},"opacity":1,"edgeAntialiasingMask":0,"height":768,"hidden":false,"anchorPoint":{"pointX":0.5,"pointY":0.5}},"texture":"894F4F28C10671A3EF251E2272519862"},{"animations":[{"repeatCount":0,"removedOnCompletion":false,"from":{"scalar":1},"timingFunction":"EaseInEaseOut","additive":false,"timeOffset":0,"autoreverses":false,"property":"opacity","fillMode":"both","duration":1,"beginTime":0,"to":{"scalar":0}}],"layers":[],"texturedRectangle":{"isBackgroundTexture":false,"singleTextureOpacity":1,"textureType":0,"textBaseline":0,"textXHeight":0,"isVerticalText":false},"initialState":{"affineTransform":[1,0,0,1,0,0],"masksToBounds":false,"rotation":0,"scale":1,"position":{"pointX":512,"pointY":384},"width":1024,"sublayerTransform":[1,0,0,0,0,1,0,0,0,0,1,0,0,0,0,1],"contentsRect":{"y":0,"x":0,"width":1,"height":1},"opacity":1,"edgeAntialiasingMask":0,"height":768,"hidden":false,"anchorPoint":{"pointX":0.5,"pointY":0.5}},"texture":"A368F5FCC70D94AF31308A4D34DC4497"}]}]},"effects":[],"duration":1,"type":"transition","attributes":{"direction":13},"name":"com.apple.iWork.Keynote.BUKFlop","objectID":"0"}],"automaticPlay":false,"hyperlinks":[],"accessibility":[{"text":"2.4 Modificación Resultados de Aprendizaje","targetRectangle":{"y":79.818023681640625,"x":212.69708984375001,"width":598.60582031249987,"height":45}}],"baseLayer":{"animations":[],"initialState":{"affineTransform":[1,0,0,1,0,0],"masksToBounds":false,"rotation":0,"scale":1,"position":{"pointX":512,"pointY":384},"width":1024,"sublayerTransform":[1,0,0,0,0,1,0,0,0,0,1,0,0,0,0,1],"contentsRect":{"y":0,"x":0,"width":1,"height":1},"opacity":1,"edgeAntialiasingMask":251658240,"height":768,"hidden":false,"anchorPoint":{"pointX":0.5,"pointY":0.5}},"objectID":"0","layers":[{"animations":[],"initialState":{"affineTransform":[1,0,0,1,0,0],"masksToBounds":false,"rotation":0,"scale":1,"position":{"pointX":512,"pointY":384},"width":1024,"sublayerTransform":[1,0,0,0,0,1,0,0,0,0,1,-0.00049229876906403734,0,0,0,1],"contentsRect":{"y":0,"x":0,"width":1,"height":1},"opacity":1,"edgeAntialiasingMask":251658240,"height":768,"hidden":false,"anchorPoint":{"pointX":0.5,"pointY":0.5}},"layers":[{"animations":[],"layers":[],"texturedRectangle":{"isBackgroundTexture":false,"singleTextureOpacity":1,"textureType":0,"textBaseline":0,"textXHeight":0,"isVerticalText":false},"initialState":{"affineTransform":[1,0,0,1,0,0],"masksToBounds":false,"rotation":0,"scale":1,"position":{"pointX":512,"pointY":384},"width":1024,"sublayerTransform":[1,0,0,0,0,1,0,0,0,0,1,0,0,0,0,1],"contentsRect":{"y":0,"x":0,"width":1,"height":1},"opacity":1,"edgeAntialiasingMask":0,"height":768,"hidden":false,"anchorPoint":{"pointX":0.5,"pointY":0.5}},"texture":"A368F5FCC70D94AF31308A4D34DC4497"}]}]}}]}